packPOOII/__init__.py
packPOOII/packPOOII.py
packPOOII-0.0.3.6.dist-info/LICENSE
packPOOII-0.0.3.6.dist-info/METADATA
packPOOII-0.0.3.6.dist-info/WHEEL
packPOOII-0.0.3.6.dist-info/top_level.txt
packPOOII-0.0.3.6.dist-info/RECORD
