Metadata-Version: 2.1
Name: packPOOII
Version: 0.0.3.6
Summary: Pacote utilizado para fazer alterações em arquivos de texto
Home-page: https://github.com/Cicero777/POOII-Trabalho-Final
Author: Cicero Neto, Carlos Daniel
Author-email: ciceroneto02si@gmail.com
License: UNKNOWN
Project-URL: Bug Tracker, https://github.com/Cicero777/POOII-Trabalho-Final
Platform: UNKNOWN
Classifier: Programming Language :: Python :: 3
Classifier: License :: OSI Approved :: MIT License
Classifier: Operating System :: OS Independent
Requires-Python: >=3.0
License-File: LICENSE
